odoo10_addon_account_permanent_lock_move-10.0.1.0.0-py2.7-nspkg.pth
odoo/addons/account_permanent_lock_move/README.rst
odoo/addons/account_permanent_lock_move/__init__.py
odoo/addons/account_permanent_lock_move/__manifest__.py
odoo/addons/account_permanent_lock_move/i18n/am.po
odoo/addons/account_permanent_lock_move/i18n/ar.po
odoo/addons/account_permanent_lock_move/i18n/bs.po
odoo/addons/account_permanent_lock_move/i18n/ca.po
odoo/addons/account_permanent_lock_move/i18n/ca_ES.po
odoo/addons/account_permanent_lock_move/i18n/cs.po
odoo/addons/account_permanent_lock_move/i18n/de.po
odoo/addons/account_permanent_lock_move/i18n/el_GR.po
odoo/addons/account_permanent_lock_move/i18n/en_GB.po
odoo/addons/account_permanent_lock_move/i18n/es.po
odoo/addons/account_permanent_lock_move/i18n/es_CR.po
odoo/addons/account_permanent_lock_move/i18n/es_EC.po
odoo/addons/account_permanent_lock_move/i18n/es_ES.po
odoo/addons/account_permanent_lock_move/i18n/es_MX.po
odoo/addons/account_permanent_lock_move/i18n/es_VE.po
odoo/addons/account_permanent_lock_move/i18n/et.po
odoo/addons/account_permanent_lock_move/i18n/fi.po
odoo/addons/account_permanent_lock_move/i18n/fr.po
odoo/addons/account_permanent_lock_move/i18n/gl.po
odoo/addons/account_permanent_lock_move/i18n/gl_ES.po
odoo/addons/account_permanent_lock_move/i18n/gu.po
odoo/addons/account_permanent_lock_move/i18n/hr.po
odoo/addons/account_permanent_lock_move/i18n/hr_HR.po
odoo/addons/account_permanent_lock_move/i18n/hu.po
odoo/addons/account_permanent_lock_move/i18n/id.po
odoo/addons/account_permanent_lock_move/i18n/it.po
odoo/addons/account_permanent_lock_move/i18n/ja.po
odoo/addons/account_permanent_lock_move/i18n/lt.po
odoo/addons/account_permanent_lock_move/i18n/mk.po
odoo/addons/account_permanent_lock_move/i18n/mn.po
odoo/addons/account_permanent_lock_move/i18n/nb.po
odoo/addons/account_permanent_lock_move/i18n/nl.po
odoo/addons/account_permanent_lock_move/i18n/nl_BE.po
odoo10_addon_account_permanent_lock_move-10.0.1.0.0.dist-info/DESCRIPTION.rst
odoo10_addon_account_permanent_lock_move-10.0.1.0.0.dist-info/METADATA
odoo10_addon_account_permanent_lock_move-10.0.1.0.0.dist-info/RECORD
odoo10_addon_account_permanent_lock_move-10.0.1.0.0.dist-info/WHEEL
odoo10_addon_account_permanent_lock_move-10.0.1.0.0.dist-info/metadata.json
odoo10_addon_account_permanent_lock_move-10.0.1.0.0.dist-info/namespace_packages.txt
odoo10_addon_account_permanent_lock_move-10.0.1.0.0.dist-info/top_level.txt
